LICENSE
pkce_flow/__init__.py
pkce_flow/adapters.py
pkce_flow/exceptions.py
pkce_flow/managers.py
pkce_flow-0.1.2.dist-info/entry_points.txt
pkce_flow-0.1.2.dist-info/LICENSE
pkce_flow-0.1.2.dist-info/WHEEL
pkce_flow-0.1.2.dist-info/METADATA
pkce_flow-0.1.2.dist-info/RECORD
