Metadata-Version: 2.1
Name: pkce-flow
Version: 0.1.2
Summary: A utility for obtaining access tokens using the PKCE-enhanced authorization code flow (Oauth)
Home-page: https://gitlab.com/a-thousand-juniors/pkce-flow
License: MIT
Keywords: oauth,pkce
Author: Mfon Eti-mfon
Author-email: mfonetimfon@gmail.com
Requires-Python: >=3.8,<4.0
Classifier: Environment :: Web Environment
Classifier: License :: OSI Approved :: MIT License
Classifier: Operating System :: OS Independent
Classifier: Programming Language :: Python
Classifier: Programming Language :: Python :: 3
Classifier: Programming Language :: Python :: 3.8
Classifier: Programming Language :: Python :: 3.9
Requires-Dist: requests (>=2.25.1,<3.0.0)
Project-URL: Repository, https://gitlab.com/a-thousand-juniors/pkce-flow
